sidd.py
I_Am_Sidd-0.0.1.dist-info/LICENSE
I_Am_Sidd-0.0.1.dist-info/METADATA
I_Am_Sidd-0.0.1.dist-info/WHEEL
I_Am_Sidd-0.0.1.dist-info/top_level.txt
I_Am_Sidd-0.0.1.dist-info/RECORD
